PySimpleGUI27/PySimpleGUI27.py
PySimpleGUI27/__init__.py
PySimpleGUI27-1.13.0.dist-info/METADATA
PySimpleGUI27-1.13.0.dist-info/WHEEL
PySimpleGUI27-1.13.0.dist-info/top_level.txt
PySimpleGUI27-1.13.0.dist-info/RECORD
