Metadata-Version: 2.1
Name: PySimpleGUI27
Version: 1.13.0
Summary: Python 2.7 version of PySimpleGUI - GUI SDK Launched in 2018 Actively developed and supported. Super-simple to create custom GUI's.  Python 2.7 & 3 Support. 100 Demo programs & Cookbook for rapid start. Extensive documentation. Examples using Machine Learning(GUI, OpenCV Integration,  Chatterbot), Rainmeter Style Floating Desktop Widgets, Matplotlib + Pyplot integration, add GUI to command line scripts, PDF & Image Viewer. Great for beginners as well as advanced GUI programmers
Home-page: https://github.com/MikeTheWatchGuy/PySimpleGUI
Author: MikeTheWatchGuy
Author-email: mike@PySimpleGUI.com
License: UNKNOWN
Keywords: GUI UI tkinter wrapper simple easy beginner novice student graphics progressbar progressmeter
Platform: UNKNOWN
Classifier: Programming Language :: Python :: 2.7
Classifier: License :: OSI Approved :: GNU Lesser General Public License v3 or later (LGPLv3+)
Classifier: Topic :: Multimedia :: Graphics
Classifier: Operating System :: OS Independent
Requires-Dist: future
